Workbook

Sheet Dashboard
A1: Adobe Stock Intelligence Dashboard v2
A3: KPI | B3: Value | D3: Industry | E3: Target Niches | F3: Researched | G3: Avg Score | H3: Status
A4: Total Niches | B4: =COUNTA('Niche Database'!B2:B501) -> 10 | D4: Healthcare | E4: =IFERROR(VLOOKUP(D4,'Industry Database'!A:E,3,FALSE()),"") -> 25 | F4: =IFERROR(VLOOKUP(D4,'Industry Database'!A:E,4,FALSE()),"") -> 1 | G4: =IFERROR(VLOOKUP(D4,'Industry Database'!A:E,5,FALSE()),"") -> 84 | H4: =IF(G4>=80,"Invest",IF(G4>=60,"Watch","Avoid")) -> Invest
A5: Researched Niches | B5: =COUNTA('Niche Database'!M2:M501) -> 500 | D5: FMCG & Packaging | E5: =IFERROR(VLOOKUP(D5,'Industry Database'!A:E,3,FALSE()),"") -> 25 | F5: =IFERROR(VLOOKUP(D5,'Industry Database'!A:E,4,FALSE()),"") -> 2 | G5: =IFERROR(VLOOKUP(D5,'Industry Database'!A:E,5,FALSE()),"") -> 71 | H5: =IF(G5>=80,"Invest",IF(G5>=60,"Watch","Avoid")) -> Watch
A6: High Priority Niches | B6: =COUNTIF('Niche Database'!N:N,"High") -> 8 | D6: Pet | E6: =IFERROR(VLOOKUP(D6,'Industry Database'!A:E,3,FALSE()),"") -> 25 | F6: =IFERROR(VLOOKUP(D6,'Industry Database'!A:E,4,FALSE()),"") -> 1 | G6: =IFERROR(VLOOKUP(D6,'Industry Database'!A:E,5,FALSE()),"") -> 82 | H6: =IF(G6>=80,"Invest",IF(G6>=60,"Watch","Avoid")) -> Invest
A7: Avg Opportunity Score | B7: =ROUND(AVERAGE('Niche Database'!M2:M501),0) -> 34 | D7: Manufacturing | E7: =IFERROR(VLOOKUP(D7,'Industry Database'!A:E,3,FALSE()),"") -> 25 | F7: =IFERROR(VLOOKUP(D7,'Industry Database'!A:E,4,FALSE()),"") -> 1 | G7: =IFERROR(VLOOKUP(D7,'Industry Database'!A:E,5,FALSE()),"") -> 79 | H7: =IF(G7>=80,"Invest",IF(G7>=60,"Watch","Avoid")) -> Watch
A8: Images Uploaded | B8: =COUNTA('Portfolio Tracker'!A2:A500) -> 3 | D8: Retail | E8: =IFERROR(VLOOKUP(D8,'Industry Database'!A:E,3,FALSE()),"") -> 25 | F8: =IFERROR(VLOOKUP(D8,'Industry Database'!A:E,4,FALSE()),"") -> 1 | G8: =IFERROR(VLOOKUP(D8,'Industry Database'!A:E,5,FALSE()),"") -> 74 | H8: =IF(G8>=80,"Invest",IF(G8>=60,"Watch","Avoid")) -> Watch
A9: Downloads | B9: =SUM('Portfolio Tracker'!F2:F500) -> 0 | D9: Technology | E9: =IFERROR(VLOOKUP(D9,'Industry Database'!A:E,3,FALSE()),"") -> 25 | F9: =IFERROR(VLOOKUP(D9,'Industry Database'!A:E,4,FALSE()),"") -> 1 | G9: =IFERROR(VLOOKUP(D9,'Industry Database'!A:E,5,FALSE()),"") -> 66 | H9: =IF(G9>=80,"Invest",IF(G9>=60,"Watch","Avoid")) -> Watch
A10: Revenue | B10: =SUM('Portfolio Tracker'!G2:G500) -> 0 | D10: Construction | E10: =IFERROR(VLOOKUP(D10,'Industry Database'!A:E,3,FALSE()),"") -> 25 | F10: =IFERROR(VLOOKUP(D10,'Industry Database'!A:E,4,FALSE()),"") -> 1 | G10: =IFERROR(VLOOKUP(D10,'Industry Database'!A:E,5,FALSE()),"") -> 74 | H10: =IF(G10>=80,"Invest",IF(G10>=60,"Watch","Avoid")) -> Watch
A11: Best Niche | B11: =IFERROR(INDEX('Niche Database'!B:B,MATCH(MAX('Niche Database'!M:M),'Niche Database'!M:M,0)),"") -> Empty pharmacy shelf | D11: Education | E11: =IFERROR(VLOOKUP(D11,'Industry Database'!A:E,3,FALSE()),"") -> 25 | F11: =IFERROR(VLOOKUP(D11,'Industry Database'!A:E,4,FALSE()),"") -> 0 | G11: =IFERROR(VLOOKUP(D11,'Industry Database'!A:E,5,FALSE()),"") | H11: =IF(G11>=80,"Invest",IF(G11>=60,"Watch","Avoid")) -> Invest
A12: Worst Niche | B12: =IFERROR(INDEX('Niche Database'!B:B,MATCH(MIN('Niche Database'!M2:M501),'Niche Database'!M:M,0)),"") -> 0 | D12: Finance | E12: =IFERROR(VLOOKUP(D12,'Industry Database'!A:E,3,FALSE()),"") -> 25 | F12: =IFERROR(VLOOKUP(D12,'Industry Database'!A:E,4,FALSE()),"") -> 1 | G12: =IFERROR(VLOOKUP(D12,'Industry Database'!A:E,5,FALSE()),"") -> 76 | H12: =IF(G12>=80,"Invest",IF(G12>=60,"Watch","Avoid")) -> Watch
D13: Hospitality | E13: =IFERROR(VLOOKUP(D13,'Industry Database'!A:E,3,FALSE()),"") -> 25 | F13: =IFERROR(VLOOKUP(D13,'Industry Database'!A:E,4,FALSE()),"") -> 0 | G13: =IFERROR(VLOOKUP(D13,'Industry Database'!A:E,5,FALSE()),"") | H13: =IF(G13>=80,"Invest",IF(G13>=60,"Watch","Avoid")) -> Invest
A15: Top Opportunity Niches | B15: Industry | C15: Buyer | D15: Score | E15: Priority | F15: Status
A16: =IFERROR(INDEX('Niche Database'!$B:$B,MATCH(LARGE('Niche Database'!$M$2:$M$501,1),'Niche Database'!$M:$M,0)),"") -> Empty pharmacy shelf | B16: =IFERROR(INDEX('Niche Database'!$A:$A,MATCH(A16,'Niche Database'!$B:$B,0)),"") -> Healthcare | C16: =IFERROR(INDEX('Niche Database'!$C:$C,MATCH(A16,'Niche Database'!$B:$B,0)),"") -> Healthcare marketer | D16: =IFERROR(INDEX('Niche Database'!$M:$M,MATCH(A16,'Niche Database'!$B:$B,0)),"") -> 84 | E16: =IFERROR(INDEX('Niche Database'!$N:$N,MATCH(A16,'Niche Database'!$B:$B,0)),"") -> High | F16: =IFERROR(INDEX('Niche Database'!$O:$O,MATCH(A16,'Niche Database'!$B:$B,0)),"") -> Research
A17: =IFERROR(INDEX('Niche Database'!$B:$B,MATCH(LARGE('Niche Database'!$M$2:$M$501,2),'Niche Database'!$M:$M,0)),"") -> Pet food packaging display | B17: =IFERROR(INDEX('Niche Database'!$A:$A,MATCH(A17,'Niche Database'!$B:$B,0)),"") -> Pet | C17: =IFERROR(INDEX('Niche Database'!$C:$C,MATCH(A17,'Niche Database'!$B:$B,0)),"") -> Pet brand owner | D17: =IFERROR(INDEX('Niche Database'!$M:$M,MATCH(A17,'Niche Database'!$B:$B,0)),"") -> 82 | E17: =IFERROR(INDEX('Niche Database'!$N:$N,MATCH(A17,'Niche Database'!$B:$B,0)),"") -> High | F17: =IFERROR(INDEX('Niche Database'!$O:$O,MATCH(A17,'Niche Database'!$B:$B,0)),"") -> Research
A18: =IFERROR(INDEX('Niche Database'!$B:$B,MATCH(LARGE('Niche Database'!$M$2:$M$501,3),'Niche Database'!$M:$M,0)),"") -> Pet food packaging display | B18: =IFERROR(INDEX('Niche Database'!$A:$A,MATCH(A18,'Niche Database'!$B:$B,0)),"") -> Pet | C18: =IFERROR(INDEX('Niche Database'!$C:$C,MATCH(A18,'Niche Database'!$B:$B,0)),"") -> Pet brand owner | D18: =IFERROR(INDEX('Niche Database'!$M:$M,MATCH(A18,'Niche Database'!$B:$B,0)),"") -> 82 | E18: =IFERROR(INDEX('Niche Database'!$N:$N,MATCH(A18,'Niche Database'!$B:$B,0)),"") -> High | F18: =IFERROR(INDEX('Niche Database'!$O:$O,MATCH(A18,'Niche Database'!$B:$B,0)),"") -> Research
A19: =IFERROR(INDEX('Niche Database'!$B:$B,MATCH(LARGE('Niche Database'!$M$2:$M$501,4),'Niche Database'!$M:$M,0)),"") -> Clean industrial workbench | B19: =IFERROR(INDEX('Niche Database'!$A:$A,MATCH(A19,'Niche Database'!$B:$B,0)),"") -> Manufacturing | C19: =IFERROR(INDEX('Niche Database'!$C:$C,MATCH(A19,'Niche Database'!$B:$B,0)),"") -> B2B manufacturer | D19: =IFERROR(INDEX('Niche Database'!$M:$M,MATCH(A19,'Niche Database'!$B:$B,0)),"") -> 79 | E19: =IFERROR(INDEX('Niche Database'!$N:$N,MATCH(A19,'Niche Database'!$B:$B,0)),"") -> High | F19: =IFERROR(INDEX('Niche Database'!$O:$O,MATCH(A19,'Niche Database'!$B:$B,0)),"") -> Research
A20: =IFERROR(INDEX('Niche Database'!$B:$B,MATCH(LARGE('Niche Database'!$M$2:$M$501,5),'Niche Database'!$M:$M,0)),"") -> Bank teller window | B20: =IFERROR(INDEX('Niche Database'!$A:$A,MATCH(A20,'Niche Database'!$B:$B,0)),"") -> Finance | C20: =IFERROR(INDEX('Niche Database'!$C:$C,MATCH(A20,'Niche Database'!$B:$B,0)),"") -> Banking / fintech marketer | D20: =IFERROR(INDEX('Niche Database'!$M:$M,MATCH(A20,'Niche Database'!$B:$B,0)),"") -> 76 | E20: =IFERROR(INDEX('Niche Database'!$N:$N,MATCH(A20,'Niche Database'!$B:$B,0)),"") -> High | F20: =IFERROR(INDEX('Niche Database'!$O:$O,MATCH(A20,'Niche Database'!$B:$B,0)),"") -> Research
A21: =IFERROR(INDEX('Niche Database'!$B:$B,MATCH(LARGE('Niche Database'!$M$2:$M$501,6),'Niche Database'!$M:$M,0)),"") -> Retail end-cap display | B21: =IFERROR(INDEX('Niche Database'!$A:$A,MATCH(A21,'Niche Database'!$B:$B,0)),"") -> Retail | C21: =IFERROR(INDEX('Niche Database'!$C:$C,MATCH(A21,'Niche Database'!$B:$B,0)),"") -> Retail merchandising marketer | D21: =IFERROR(INDEX('Niche Database'!$M:$M,MATCH(A21,'Niche Database'!$B:$B,0)),"") -> 74 | E21: =IFERROR(INDEX('Niche Database'!$N:$N,MATCH(A21,'Niche Database'!$B:$B,0)),"") -> High | F21: =IFERROR(INDEX('Niche Database'!$O:$O,MATCH(A21,'Niche Database'!$B:$B,0)),"") -> Research
A22: =IFERROR(INDEX('Niche Database'!$B:$B,MATCH(LARGE('Niche Database'!$M$2:$M$501,7),'Niche Database'!$M:$M,0)),"") -> Retail end-cap display | B22: =IFERROR(INDEX('Niche Database'!$A:$A,MATCH(A22,'Niche Database'!$B:$B,0)),"") -> Retail | C22: =IFERROR(INDEX('Niche Database'!$C:$C,MATCH(A22,'Niche Database'!$B:$B,0)),"") -> Retail merchandising marketer | D22: =IFERROR(INDEX('Niche Database'!$M:$M,MATCH(A22,'Niche Database'!$B:$B,0)),"") -> 74 | E22: =IFERROR(INDEX('Niche Database'!$N:$N,MATCH(A22,'Niche Database'!$B:$B,0)),"") -> High | F22: =IFERROR(INDEX('Niche Database'!$O:$O,MATCH(A22,'Niche Database'!$B:$B,0)),"") -> Research
A23: =IFERROR(INDEX('Niche Database'!$B:$B,MATCH(LARGE('Niche Database'!$M$2:$M$501,8),'Niche Database'!$M:$M,0)),"") -> Warehouse loading dock interior | B23: =IFERROR(INDEX('Niche Database'!$A:$A,MATCH(A23,'Niche Database'!$B:$B,0)),"") -> Logistics | C23: =IFERROR(INDEX('Niche Database'!$C:$C,MATCH(A23,'Niche Database'!$B:$B,0)),"") -> Logistics / 3PL marketer | D23: =IFERROR(INDEX('Niche Database'!$M:$M,MATCH(A23,'Niche Database'!$B:$B,0)),"") -> 71 | E23: =IFERROR(INDEX('Niche Database'!$N:$N,MATCH(A23,'Niche Database'!$B:$B,0)),"") -> High | F23: =IFERROR(INDEX('Niche Database'!$O:$O,MATCH(A23,'Niche Database'!$B:$B,0)),"") -> Research
A24: =IFERROR(INDEX('Niche Database'!$B:$B,MATCH(LARGE('Niche Database'!$M$2:$M$501,9),'Niche Database'!$M:$M,0)),"") -> Empty server room | B24: =IFERROR(INDEX('Niche Database'!$A:$A,MATCH(A24,'Niche Database'!$B:$B,0)),"") -> Technology | C24: =IFERROR(INDEX('Niche Database'!$C:$C,MATCH(A24,'Niche Database'!$B:$B,0)),"") -> SaaS / IT marketer | D24: =IFERROR(INDEX('Niche Database'!$M:$M,MATCH(A24,'Niche Database'!$B:$B,0)),"") -> 66 | E24: =IFERROR(INDEX('Niche Database'!$N:$N,MATCH(A24,'Niche Database'!$B:$B,0)),"") -> Medium | F24: =IFERROR(INDEX('Niche Database'!$O:$O,MATCH(A24,'Niche Database'!$B:$B,0)),"") -> Research
A25: =IFERROR(INDEX('Niche Database'!$B:$B,MATCH(LARGE('Niche Database'!$M$2:$M$501,10),'Niche Database'!$M:$M,0)),"") -> Luxury product podium | B25: =IFERROR(INDEX('Niche Database'!$A:$A,MATCH(A25,'Niche Database'!$B:$B,0)),"") -> FMCG & Packaging | C25: =IFERROR(INDEX('Niche Database'!$C:$C,MATCH(A25,'Niche Database'!$B:$B,0)),"") -> Beauty marketer | D25: =IFERROR(INDEX('Niche Database'!$M:$M,MATCH(A25,'Niche Database'!$B:$B,0)),"") -> 59 | E25: =IFERROR(INDEX('Niche Database'!$N:$N,MATCH(A25,'Niche Database'!$B:$B,0)),"") -> Avoid | F25: =IFERROR(INDEX('Niche Database'!$O:$O,MATCH(A25,'Niche Database'!$B:$B,0)),"") -> Avoid

Sheet Industry Database
A1: Industry | B1: Priority | C1: Target Niches | D1: Researched Niches | E1: Avg Opportunity Score | F1: Top Niche | G1: Status | H1: Notes
A2: Healthcare | B2: High | C2: 25 | D2: =COUNTIF('Niche Database'!$A$2:$A$501,A2) -> 1 | E2: =IFERROR(ROUND(SUMIF('Niche Database'!$A$2:$A$501,A2,'Niche Database'!$M$2:$M$501)/COUNTIF('Niche Database'!$A$2:$A$501,A2),0),"") -> 84 | F2: =IFERROR(INDEX('Niche Database'!$B$2:$B$501,MATCH(1,('Niche Database'!$A$2:$A$501=A2)*('Niche Database'!$M$2:$M$501=E2),0)),"") -> Empty pharmacy shelf | G2: Research
A3: FMCG & Packaging | B3: High | C3: 25 | D3: =COUNTIF('Niche Database'!$A$2:$A$501,A3) -> 2 | E3: =IFERROR(ROUND(SUMIF('Niche Database'!$A$2:$A$501,A3,'Niche Database'!$M$2:$M$501)/COUNTIF('Niche Database'!$A$2:$A$501,A3),0),"") -> 71 | F3: =IFERROR(INDEX('Niche Database'!$B$2:$B$501,MATCH(1,('Niche Database'!$A$2:$A$501=A3)*('Niche Database'!$M$2:$M$501=E3),0)),"") | G3: Research
A4: Pet | B4: High | C4: 25 | D4: =COUNTIF('Niche Database'!$A$2:$A$501,A4) -> 1 | E4: =IFERROR(ROUND(SUMIF('Niche Database'!$A$2:$A$501,A4,'Niche Database'!$M$2:$M$501)/COUNTIF('Niche Database'!$A$2:$A$501,A4),0),"") -> 82 | F4: =IFERROR(INDEX('Niche Database'!$B$2:$B$501,MATCH(1,('Niche Database'!$A$2:$A$501=A4)*('Niche Database'!$M$2:$M$501=E4),0)),"") -> Pet food packaging display | G4: Research
A5: Manufacturing | B5: High | C5: 25 | D5: =COUNTIF('Niche Database'!$A$2:$A$501,A5) -> 1 | E5: =IFERROR(ROUND(SUMIF('Niche Database'!$A$2:$A$501,A5,'Niche Database'!$M$2:$M$501)/COUNTIF('Niche Database'!$A$2:$A$501,A5),0),"") -> 79 | F5: =IFERROR(INDEX('Niche Database'!$B$2:$B$501,MATCH(1,('Niche Database'!$A$2:$A$501=A5)*('Niche Database'!$M$2:$M$501=E5),0)),"") -> Clean industrial workbench | G5: Research
A6: Retail | B6: High | C6: 25 | D6: =COUNTIF('Niche Database'!$A$2:$A$501,A6) -> 1 | E6: =IFERROR(ROUND(SUMIF('Niche Database'!$A$2:$A$501,A6,'Niche Database'!$M$2:$M$501)/COUNTIF('Niche Database'!$A$2:$A$501,A6),0),"") -> 74 | F6: =IFERROR(INDEX('Niche Database'!$B$2:$B$501,MATCH(1,('Niche Database'!$A$2:$A$501=A6)*('Niche Database'!$M$2:$M$501=E6),0)),"") -> Retail end-cap display | G6: Research
A7: Technology | B7: Medium | C7: 25 | D7: =COUNTIF('Niche Database'!$A$2:$A$501,A7) -> 1 | E7: =IFERROR(ROUND(SUMIF('Niche Database'!$A$2:$A$501,A7,'Niche Database'!$M$2:$M$501)/COUNTIF('Niche Database'!$A$2:$A$501,A7),0),"") -> 66 | F7: =IFERROR(INDEX('Niche Database'!$B$2:$B$501,MATCH(1,('Niche Database'!$A$2:$A$501=A7)*('Niche Database'!$M$2:$M$501=E7),0)),"") -> Empty server room | G7: Research
A8: Construction | B8: Medium | C8: 25 | D8: =COUNTIF('Niche Database'!$A$2:$A$501,A8) -> 1 | E8: =IFERROR(ROUND(SUMIF('Niche Database'!$A$2:$A$501,A8,'Niche Database'!$M$2:$M$501)/COUNTIF('Niche Database'!$A$2:$A$501,A8),0),"") -> 74 | F8: =IFERROR(INDEX('Niche Database'!$B$2:$B$501,MATCH(1,('Niche Database'!$A$2:$A$501=A8)*('Niche Database'!$M$2:$M$501=E8),0)),"") -> Construction site office trailer | G8: Research
A9: Education | B9: Medium | C9: 25 | D9: =COUNTIF('Niche Database'!$A$2:$A$501,A9) -> 0 | E9: =IFERROR(ROUND(SUMIF('Niche Database'!$A$2:$A$501,A9,'Niche Database'!$M$2:$M$501)/COUNTIF('Niche Database'!$A$2:$A$501,A9),0),"") | F9: =IFERROR(INDEX('Niche Database'!$B$2:$B$501,MATCH(1,('Niche Database'!$A$2:$A$501=A9)*('Niche Database'!$M$2:$M$501=E9),0)),"") | G9: Research
A10: Finance | B10: Medium | C10: 25 | D10: =COUNTIF('Niche Database'!$A$2:$A$501,A10) -> 1 | E10: =IFERROR(ROUND(SUMIF('Niche Database'!$A$2:$A$501,A10,'Niche Database'!$M$2:$M$501)/COUNTIF('Niche Database'!$A$2:$A$501,A10),0),"") -> 76 | F10: =IFERROR(INDEX('Niche Database'!$B$2:$B$501,MATCH(1,('Niche Database'!$A$2:$A$501=A10)*('Niche Database'!$M$2:$M$501=E10),0)),"") -> Bank teller window | G10: Research
A11: Hospitality | B11: Medium | C11: 25 | D11: =COUNTIF('Niche Database'!$A$2:$A$501,A11) -> 0 | E11: =IFERROR(ROUND(SUMIF('Niche Database'!$A$2:$A$501,A11,'Niche Database'!$M$2:$M$501)/COUNTIF('Niche Database'!$A$2:$A$501,A11),0),"") | F11: =IFERROR(INDEX('Niche Database'!$B$2:$B$501,MATCH(1,('Niche Database'!$A$2:$A$501=A11)*('Niche Database'!$M$2:$M$501=E11),0)),"") | G11: Research
A12: Logistics | B12: Medium | C12: 25 | D12: =COUNTIF('Niche Database'!$A$2:$A$501,A12) -> 1 | E12: =IFERROR(ROUND(SUMIF('Niche Database'!$A$2:$A$501,A12,'Niche Database'!$M$2:$M$501)/COUNTIF('Niche Database'!$A$2:$A$501,A12),0),"") -> 71 | F12: =IFERROR(INDEX('Niche Database'!$B$2:$B$501,MATCH(1,('Niche Database'!$A$2:$A$501=A12)*('Niche Database'!$M$2:$M$501=E12),0)),"") -> Warehouse loading dock interior | G12: Research
A13: Energy | B13: Medium | C13: 25 | D13: =COUNTIF('Niche Database'!$A$2:$A$501,A13) -> 0 | E13: =IFERROR(ROUND(SUMIF('Niche Database'!$A$2:$A$501,A13,'Niche Database'!$M$2:$M$501)/COUNTIF('Niche Database'!$A$2:$A$501,A13),0),"") | F13: =IFERROR(INDEX('Niche Database'!$B$2:$B$501,MATCH(1,('Niche Database'!$A$2:$A$501=A13)*('Niche Database'!$M$2:$M$501=E13),0)),"") | G13: Research
... A16: Beauty | B16: Medium | C16: 25 | D16: =COUNTIF('Niche Database'!$A$2:$A$501,A16) -> 0 | E16: =IFERROR(ROUND(SUMIF('Niche Database'!$A$2:$A$501,A16,'Niche Database'!$M$2:$M$501)/COUNTIF('Niche Database'!$A$2:$A$501,A16),0),"") | F16: =IFERROR(INDEX('Niche Database'!$B$2:$B$501,MATCH(1,('Niche Database'!$A$2:$A$501=A16)*('Niche Database'!$M$2:$M$501=E16),0)),"") | G16: Research

Sheet Niche Database
A1: Industry | B1: Niche | C1: Buyer Persona | D1: Job To Be Done | E1: Adobe Results | F1: Shutterstock Results | G1: Demand (1-10) | H1: Competition (1-10) | I1: Commercial Value (1-10) | J1: Evergreen (1-10) | K1: Repeat Use (1-10) | L1: AI Saturation (1-10) | M1: Opportunity Score | N1: Priority | O1: Status | P1: Next Action | Q1: Source URL | R1: Notes
A2: Healthcare | B2: Empty pharmacy shelf | C2: Healthcare marketer | D2: Website hero, supplement ad, pharmacy banner | E2: 3000 | F2: 12000 | G2: 8 | H2: 3 | I2: 9 | J2: 9 | K2: 9 | L2: 3 | M2: =ROUND(((G2*30)+((11-H2)*25)+(I2*20)+(J2*10)+(K2*10)+((11-L2)*5))/10,0) -> 84 | N2: High | O2: Research | P2: Check top 100 thumbnails | Q2: https://stock.adobe.com/ | R2: Low supply vs strong commercial use
A3: Pet | B3: Pet food packaging display | C3: Pet brand owner | D3: Packaging mockup, social ad, ecommerce banner | E3: 5000 | F3: 18000 | G3: 8 | H3: 3 | I3: 9 | J3: 8 | K3: 8 | L3: 3 | M3: =ROUND(((G3*30)+((11-H3)*25)+(I3*20)+(J3*10)+(K3*10)+((11-L3)*5))/10,0) -> 82 | N3: High | O3: Research | P3: Create 10 prompt tests | Q3: https://stock.adobe.com/ | R3: Strong fit with user's pet brand interest
A4: FMCG & Packaging | B4: Frozen food freezer display | C4: FMCG brand manager | D4: Retail mockup, sales deck, ecommerce banner | E4: 8000 | F4: 25000 | G4: 7 | H4: 2 | I4: 9 | J4: 8 | K4: 8 | L4: 3 | M4: =ROUND(((G4*30)+((11-H4)*25)+(I4*20)+(J4*10)+(K4*10)+((11-L4)*5))/10,0) -> 82 | N4: High | O4: Research | P4: Audit competitor style | Q4: https://stock.adobe.com/ | R4: Useful and less AI saturated
A5: FMCG & Packaging | B5: Luxury product podium | C5: Beauty marketer | D5: Generic product background | E5: 3600000 | F5: 9000000 | G5: 9 | H5: 10 | I5: 7 | J5: 7 | K5: 7 | L5: 9 | M5: =ROUND(((G5*30)+((11-H5)*25)+(I5*20)+(J5*10)+(K5*10)+((11-L5)*5))/10,0) -> 59 | N5: Avoid | O5: Avoid | P5: Stop producing | Q5: https://stock.adobe.com/ | R5: Oversupplied red ocean
A6: Manufacturing | B6: Clean industrial workbench | C6: B2B manufacturer | D6: Website hero, brochure, capability deck | E6: 15000 | F6: 45000 | G6: 7 | H6: 3 | I6: 8 | J6: 9 | K6: 8 | L6: 2 | M6: =ROUND(((G6*30)+((11-H6)*25)+(I6*20)+(J6*10)+(K6*10)+((11-L6)*5))/10,0) -> 79 | N6: High | O6: Research | P6: Collect references | Q6: https://stock.adobe.com/ | R6: B2B evergreen opportunity
A7: Retail | B7: Retail end-cap display | C7: Retail merchandising marketer | D7: Planogram deck, trade marketing sheet, sales presentation | E7: 176 | F7: 188 | G7: 6 | H7: 2 | I7: 7 | J7: 8 | K7: 7 | L7: 2 | M7: =ROUND(((G7*30)+((11-H7)*25)+(I7*20)+(J7*10)+(K7*10)+((11-L7)*5))/10,0) -> 74 | N7: High | O7: Research | P7: Create 10 prompt tests | Q7: https://stock.adobe.com/ | R7: Adobe: 'gondola end cap' = 176 results (verified). Shutterstock: 'retail end cap' = 188 results (verified). Extremely low supply on both platforms; already flagged in Keyword Database. Niche buyer base (retail merchandisers) vs Healthcare/Pet, so Demand rated moderate not high.
A8: Technology | B8: Empty server room | C8: SaaS / IT marketer | D8: Website hero, cloud hosting ad, annual report imagery | E8: 26525 | F8: 90000 | G8: 8 | H8: 6 | I8: 7 | J8: 7 | K8: 6 | L8: 6 | M8: =ROUND(((G8*30)+((11-H8)*25)+(I8*20)+(J8*10)+(K8*10)+((11-L8)*5))/10,0) -> 66 | N8: Medium | O8: Research | P8: Audit top 50 thumbnails for AI mix before producing | Q8: https://stock.adobe.com/ | R8: Adobe: 'server room empty' = 26,525 results (verified). Shutterstock figure is an ESTIMATE (~90k, extrapolated from 'network server room' 60,759 and 'empty computer room' 111,978) - verify manually before relying on it. Category already has meaningful AI-generated 'futuristic server' supply, so Competition/AI Saturation rated mid not low.
A9: Construction | B9: Construction site office trailer | C9: Construction company marketer | D9: Website hero, capability brochure, project mgmt software ad | E9: 2655 | F9: 8000 | G9: 6 | H9: 2 | I9: 7 | J9: 8 | K9: 7 | L9: 3 | M9: =ROUND(((G9*30)+((11-H9)*25)+(I9*20)+(J9*10)+(K9*10)+((11-L9)*5))/10,0) -> 74 | N9: High | O9: Research | P9: Collect references, create 10 prompt tests | Q9: https://stock.adobe.com/ | R9: Adobe: 'construction office trailer' = 2,655 results (verified, low supply). Shutterstock figure is an ESTIMATE - verify manually. Note: generic Construction angles tried first (blueprints, safety/PPE gear, site signage) are all oversupplied in the millions - this specific angle is the exception, not the rule for this industry.
A10: Finance | B10: Bank teller window | C10: Banking / fintech marketer | D10: Website hero, financial literacy content, banking app ad | E10: 4436 | F10: 13000 | G10: 7 | H10: 3 | I10: 8 | J10: 8 | K10: 7 | L10: 4 | M10: =ROUND(((G10*30)+((11-H10)*25)+(I10*20)+(J10*10)+(K10*10)+((11-L10)*5))/10,0) -> 76 | N10: High | O10: Research | P10: Audit competitor style, create 10 prompt tests | Q10: https://stock.adobe.com/ | R10: Adobe: 'bank teller window' = 4,436 results (verified, low-moderate supply). Shutterstock figure is an ESTIMATE - verify manually. Strongest opportunity identified in this research round.
A11: Logistics | B11: Warehouse loading dock interior | C11: Logistics / 3PL marketer | D11: Website hero, freight brokerage sales deck, capability brochure | E11: 8231 | F11: 24000 | G11: 7 | H11: 4 | I11: 7 | J11: 8 | K11: 7 | L11: 5 | M11: =ROUND(((G11*30)+((11-H11)*25)+(I11*20)+(J11*10)+(K11*10)+((11-L11)*5))/10,0) -> 71 | N11: High | O11: Research | P11: Check top 100 thumbnails | Q11: https://stock.adobe.com/ | R11: Adobe: 'warehouse loading dock interior' = 8,231 results (verified). Shutterstock figure is an ESTIMATE - verify manually.
M12: =ROUND(((G12*30)+((11-H12)*25)+(I12*20)+(J12*10)+(K12*10)+((11-L12)*5))/10,0) -> 33
M13: =ROUND(((G13*30)+((11-H13)*25)+(I13*20)+(J13*10)+(K13*10)+((11-L13)*5))/10,0) -> 33
M14: =ROUND(((G14*30)+((11-H14)*25)+(I14*20)+(J14*10)+(K14*10)+((11-L14)*5))/10,0) -> 33
M15: =ROUND(((G15*30)+((11-H15)*25)+(I15*20)+(J15*10)+(K15*10)+((11-L15)*5))/10,0) -> 33
M16: =ROUND(((G16*30)+((11-H16)*25)+(I16*20)+(J16*10)+(K16*10)+((11-L16)*5))/10,0) -> 33
M17: =ROUND(((G17*30)+((11-H17)*25)+(I17*20)+(J17*10)+(K17*10)+((11-L17)*5))/10,0) -> 33
M18: =ROUND(((G18*30)+((11-H18)*25)+(I18*20)+(J18*10)+(K18*10)+((11-L18)*5))/10,0) -> 33
M19: =ROUND(((G19*30)+((11-H19)*25)+(I19*20)+(J19*10)+(K19*10)+((11-L19)*5))/10,0) -> 33
M20: =ROUND(((G20*30)+((11-H20)*25)+(I20*20)+(J20*10)+(K20*10)+((11-L20)*5))/10,0) -> 33
M21: =ROUND(((G21*30)+((11-H21)*25)+(I21*20)+(J21*10)+(K21*10)+((11-L21)*5))/10,0) -> 33
M22: =ROUND(((G22*30)+((11-H22)*25)+(I22*20)+(J22*10)+(K22*10)+((11-L22)*5))/10,0) -> 33
M23: =ROUND(((G23*30)+((11-H23)*25)+(I23*20)+(J23*10)+(K23*10)+((11-L23)*5))/10,0) -> 33
... M501: =ROUND(((G501*30)+((11-H501)*25)+(I501*20)+(J501*10)+(K501*10)+((11-L501)*5))/10,0) -> 33

Sheet Competitor Research
A1: Date | B1: Keyword | C1: Platform | D1: Result Count | E1: Top Style | F1: AI % | G1: Photo % | H1: 3D % | I1: Top Color/Composition | J1: Gap Observed | K1: Source URL | L1: Notes
A2: 46190.252 | B2: pharmacy shelf | C2: Adobe Stock | D2: 3000 | E2: photo/3D mixed | F2: 30 | G2: 50 | H2: 20 | I2: white clinical shelves | J2: few clean empty mockup-ready shelves | K2: https://stock.adobe.com/ | L2: validate exact count manually
A3: 46190.252 | B3: product podium | C3: Adobe Stock | D3: 3600000 | E3: 3D/AI | F3: 80 | G3: 5 | H3: 15 | I3: marble, beige, pastel | J3: oversupplied | K3: https://stock.adobe.com/ | L3: avoid generic podium
A4: 46190.252 | B4: pet food packaging | C4: Adobe Stock | D4: 5000 | E4: photo/3D | F4: 35 | G4: 35 | H4: 30 | I4: retail shelf, pet aisle | J4: few premium mockup scenes | K4: https://stock.adobe.com/ | L4: high potential
A5: 46190.252 | B5: frozen food freezer | C5: Adobe Stock | D5: 8000 | E5: photo | F5: 20 | G5: 65 | H5: 15 | I5: cold blue retail | J5: few empty display layouts | K5: https://stock.adobe.com/ | L5: good for FMCG
B6: gondola end cap / retail end cap | C6: Adobe Stock + Shutterstock | D6: 176 | J6: Almost no clean retail end-cap mockups on either platform | K6: https://stock.adobe.com/ | L6: Counts verified via live search. Style/AI-Photo-3D mix not assessed this round (would need manual thumbnail review).
B7: server room empty | C7: Adobe Stock | D7: 26525 | J7: Category already has meaningful AI-generated 'futuristic server' supply | K7: https://stock.adobe.com/ | L7: Adobe count verified. Shutterstock count estimated, not verified. Style mix not assessed this round.
B8: construction office trailer | C8: Adobe Stock | D8: 2655 | J8: Generic construction angles (blueprints, PPE, signage) are all oversupplied; this specific angle is not | K8: https://stock.adobe.com/ | L8: Adobe count verified. Shutterstock count estimated, not verified. Style mix not assessed this round.
B9: bank teller window | C9: Adobe Stock | D9: 4436 | J9: Low-moderate supply for a high commercial-value B2B/fintech use case | K9: https://stock.adobe.com/ | L9: Adobe count verified. Shutterstock count estimated, not verified. Style mix not assessed this round.
B10: warehouse loading dock interior | C10: Adobe Stock | D10: 8231 | J10: Moderate supply, useful for logistics/3PL B2B marketing | K10: https://stock.adobe.com/ | L10: Adobe count verified. Shutterstock count estimated, not verified. Style mix not assessed this round.

Sheet Buyer Database
A1: Buyer Persona | B1: Industry | C1: Job To Be Done | D1: Image Needed | E1: Typical Use Case | F1: Priority | G1: Pain Point | H1: Stock Asset Direction
A2: Packaging Designer | B2: FMCG & Packaging | C2: Present packaging mockup | D2: Retail shelf, freezer, pouch display | E2: Client presentation, Behance, sales deck | F2: High | G2: Needs realistic context without brand conflict | H2: Empty packaging-ready environments
A3: Healthcare Marketer | B3: Healthcare | C3: Create trusted medical website/banner | D3: Clinic, pharmacy, medical storage | E3: Website hero, service page, ad banner | F3: High | G3: Generic medical images feel fake | H3: Clean clinical spaces without people
A4: Pet Brand Owner | B4: Pet | C4: Promote pet product online | D4: Pet retail shelf, feeding corner | E4: IG, website, ecommerce | F4: High | G4: Most pet photos are too lifestyle-heavy | H4: Premium pet product marketing scenes
A5: B2B Manufacturer | B5: Manufacturing | C5: Show capability and reliability | D5: Clean factory, workbench, warehouse | E5: Website, brochure, trade show deck | F5: High | G5: Hard to find clean industrial visuals | H5: Modern empty work environments
A6: Retail Merchandising Marketer | B6: Retail | C6: Present in-store promotional placement | D6: Clean end-cap / gondola display, empty shelf | E6: Planogram deck, trade marketing sheet | F6: Medium | G6: Hard to find a clean end-cap shot without competitor branding | H6: Empty retail fixture mockups
A7: SaaS / IT Marketer | B7: Technology | C7: Convey reliability and modern infrastructure | D7: Clean server room, data center, cloud visual | E7: Website hero, hosting ad, annual report | F7: Medium | G7: Most server room photos look dated or overly sci-fi/AI | H7: Modern, realistic clean data center scenes
A8: Construction Company Marketer | B8: Construction | C8: Show project management and professionalism | D8: Job site office, trailer, project planning scene | E8: Website hero, brochure, software ad | F8: Medium | G8: Most construction photos are generic workers/blueprints, oversupplied | H8: Specific project-management moments, not generic site shots
A9: Banking / Fintech Marketer | B9: Finance | C9: Build trust in a financial product or service | D9: Bank counter, teller window, clean financial setting | E9: Website hero, app ad, literacy content | F9: Medium | G9: Stock banking images often feel staged or outdated | H9: Modern, authentic-feeling banking scenes

Sheet Prompt Library
A1: Prompt ID | B1: Niche | C1: Industry | D1: Prompt Version | E1: Aspect Ratio | F1: Prompt | G1: Negative Rules | H1: Status | I1: Test Result | J1: Notes
A2: P001 | B2: Empty pharmacy shelf | C2: Healthcare | D2: v1 | E2: 16:9 | F2: Ultra realistic empty pharmacy shelf environment, clean medical retail display, large copy space, no products, no logos, no text, professional healthcare marketing background | G2: no people, no logos, no text, no brand names | H2: Draft
A3: P002 | B3: Pet food packaging display | C3: Pet | D3: v1 | E3: 4:5 | F3: Ultra realistic premium pet food retail display with empty packaging placement area, warm clean shelf, modern pet store background, commercial mockup-ready scene | G3: no animals, no logos, no text, no products | H3: Draft
A4: P003 | B4: Frozen food freezer display | C4: FMCG & Packaging | D4: v1 | E4: 16:9 | F4: Ultra realistic empty frozen food freezer display, clean supermarket environment, cold premium lighting, blank display zones for packaging mockup, commercial FMCG scene | G4: no logos, no text, no products, no people | H4: Draft

Sheet Portfolio Tracker
A1: Image ID | B1: Niche | C1: Industry | D1: Upload Date | E1: Approval | F1: Downloads | G1: Revenue | H1: Title | I1: Keywords | J1: Prompt ID | K1: Notes
A2: IMG001 | B2: Luxury product podium | C2: Beauty | D2: 46165.252 | E2: Approved | F2: 0 | G2: 0 | H2: Minimal product podium | I2: podium,product,background | K2: Approved but no downloads
A3: IMG002 | B3: Cosmetic display | C3: Beauty | D3: 46170.252 | E3: Approved | F3: 0 | G3: 0 | H3: Cosmetic product display | I3: beauty,cosmetic,podium | K3: High competition niche
A4: IMG003 | B4: Premium product background | C4: Beauty | D4: 46172.252 | E4: Approved | F4: 0 | G4: 0 | H4: Premium product background | I4: luxury,background,marketing | K4: Generic searchability

Sheet Keyword Database
A1: Keyword | B1: Parent Niche | C1: Intent | D1: Synonyms | E1: Commercial Value | F1: Search Notes | G1: Source URL
A2: pharmacy shelf | B2: Empty pharmacy shelf | C2: healthcare marketing | D2: medicine shelf, drugstore shelf, medical retail | E2: 9 | F2: Specific and lower supply | G2: https://stock.adobe.com/
A3: pet food packaging | B3: Pet food packaging display | C3: packaging mockup | D3: dog food bag, pet retail, pet shelf | E3: 9 | F3: Good buyer fit | G3: https://stock.adobe.com/
A4: frozen food freezer | B4: Frozen food freezer display | C4: FMCG retail | D4: supermarket freezer, frozen display | E4: 8 | F4: Useful for retail presentation | G4: https://stock.adobe.com/
A5: industrial workbench | B5: Clean industrial workbench | C5: B2B marketing | D5: factory bench, manufacturing desk | E5: 8 | F5: B2B evergreen | G5: https://stock.adobe.com/
A6: product podium | B6: Luxury product podium | C6: generic product display | D6: marble podium, cosmetic podium | E6: 5 | F6: Very high supply | G6: https://stock.adobe.com/
A7: medical storage | B7: Medical storage | C7: healthcare operation | D7: hospital storage, medicine cabinet | E7: 8 | F7: Evergreen medical B2B | G7: https://stock.adobe.com/
A8: server room empty | B8: Empty server room | C8: IT/SaaS marketing | D8: data center, server rack, cloud infrastructure | E8: 6 | F8: Moderate supply, some AI-generated variants | G8: https://stock.adobe.com/
A9: construction office trailer | B9: Construction site office trailer | C9: B2B construction marketing | D9: job site trailer, site office, portable office | E9: 7 | F9: Low supply, good B2B fit | G9: https://stock.adobe.com/
A10: bank teller window | B10: Bank teller window | C10: banking/fintech marketing | D10: bank counter, teller booth, bank window | E10: 8 | F10: Low-moderate supply, strong commercial fit | G10: https://stock.adobe.com/
A11: warehouse loading dock interior | B11: Warehouse loading dock interior | C11: logistics marketing | D11: shipping dock, freight dock, distribution center dock | E11: 7 | F11: Moderate supply, useful for logistics brands | G11: https://stock.adobe.com/

Sheet Research Queue
A1: Queue ID | B1: Keyword | C1: Industry | D1: Priority | E1: Research Status | F1: Assigned To | G1: Next Step | H1: Source URL | I1: Notes
A2: Q001 | B2: empty pharmacy shelf | C2: Healthcare | D2: High | E2: To Research | F2: Praew | G2: Record Adobe and Shutterstock results | H2: https://stock.adobe.com/
A3: Q002 | B3: pet food packaging display | C3: Pet | D3: High | E3: To Research | F3: Praew | G3: Audit top 100 thumbnails | H3: https://stock.adobe.com/
A4: Q003 | B4: frozen food freezer display | C4: FMCG & Packaging | D4: High | E4: To Research | F4: Praew | G4: Find visual gaps | H4: https://stock.adobe.com/
A5: Q004 | B5: industrial workbench | C5: Manufacturing | D5: High | E5: To Research | F5: Praew | G5: Compare photo vs AI supply | H5: https://stock.adobe.com/
A6: Q005 | B6: retail end cap display | C6: Retail | D6: Medium | E6: Done | F6: Praew | G6: Check mockup potential | H6: https://stock.adobe.com/ | I6: Researched this round - added to Niche Database, score ~74
A7: Q006 | B7: server room empty | C7: Technology | D7: Medium | E7: Done | F7: Praew | G7: Verify Shutterstock count manually | H7: https://stock.adobe.com/ | I7: Researched this round - added to Niche Database, score ~66 (Watch)
A8: Q007 | B8: construction office trailer | C8: Construction | D8: Medium | E8: Done | F8: Praew | G8: Verify Shutterstock count manually | H8: https://stock.adobe.com/ | I8: Researched this round - added to Niche Database, score ~74
A9: Q008 | B9: bank teller window | C9: Finance | D9: Medium | E9: Done | F9: Praew | G9: Verify Shutterstock count manually | H9: https://stock.adobe.com/ | I9: Researched this round - added to Niche Database, score ~76 (best of this batch)
A10: Q009 | B10: warehouse loading dock interior | C10: Logistics | D10: Medium | E10: Done | F10: Praew | G10: Verify Shutterstock count manually | H10: https://stock.adobe.com/ | I10: Researched this round - added to Niche Database, score ~71
A11: Q010 | B11: (needs a more specific angle - generic classroom/online-course terms are oversaturated) | C11: Education | D11: Medium | E11: To Research | F11: Praew | G11: Brainstorm a narrower angle, e.g. specific edtech use case | H11: https://stock.adobe.com/ | I11: Probed 'empty classroom' (315k results) and 'online course flatlay' (saturated) - both red oceans, need sharper angle
A12: Q011 | B12: (needs a more specific angle - generic hotel front desk/lobby terms are heavily supplied) | C12: Hospitality | D12: Medium | E12: To Research | F12: Praew | G12: Brainstorm a narrower angle, e.g. specific property type or moment | H12: https://stock.adobe.com/ | I12: Probed 'hotel front desk' (71k results) - oversaturated, need sharper angle
A13: Q012 | B13: (needs a more specific angle - generic control room terms are heavily supplied) | C13: Energy | D13: Medium | E13: To Research | F13: Praew | G13: Brainstorm a narrower angle, e.g. specific energy sub-sector | H13: https://stock.adobe.com/ | I13: Probed 'power control room' (132k results); 'nuclear power control room' (3.8k) more promising but narrow buyer base
A14: Q013 | B14: (needs a more specific angle - generic restaurant table/menu mockup terms are heavily supplied) | C14: Food Advertising | D14: Medium | E14: To Research | F14: Praew | G14: Brainstorm a narrower angle | H14: https://stock.adobe.com/ | I14: Probed 'empty restaurant table' (878k) and 'restaurant menu mockup' (245k) - both red oceans
A15: Q014 | B15: (needs a more specific angle - generic meeting room/office wall terms are heavily supplied) | C15: Office & Corporate | D15: Medium | E15: To Research | F15: Praew | G15: Brainstorm a narrower angle | H15: https://stock.adobe.com/ | I15: Probed 'glass conference room' (178k) and 'blank office wall' (1.3M) - both red oceans
A16: Q015 | B16: (not yet probed this round) | C16: Beauty | D16: Medium | E16: To Research | F16: Praew | G16: Start with a non-podium angle (podium/generic product bg already flagged Avoid) | H16: https://stock.adobe.com/ | I16: Not probed this round - queued for next pass

Sheet Trend Tracker
A1: Trend | B1: Industry | C1: Signal Source | D1: Signal Strength (1-10) | E1: Evergreen Risk | F1: Related Niches | G1: Action
A2: Pet wellness | B2: Pet | C2: Market/category growth | D2: 8 | E2: Low | F2: pet supplement, pet food packaging, pet feeding corner | G2: Research
A3: Healthcare retail | B3: Healthcare | C3: Evergreen demand | D3: 8 | E3: Low | F3: pharmacy shelf, medical storage, wellness clinic | G3: Research
A4: Sustainable packaging | B4: FMCG & Packaging | C4: Brand marketing trend | D4: 8 | E4: Medium | F4: eco packaging, recycled shelf, refill station | G4: Watch
A5: AI workplace | B5: Technology | C5: Trend demand | D5: 7 | E5: High | F5: AI office, automation dashboard, server room | G5: Selective
A6: Clean manufacturing | B6: Manufacturing | C6: B2B evergreen | D6: 7 | E6: Low | F6: industrial workbench, warehouse automation, clean factory | G6: Research

Sheet Settings
A1: Status | B1: Priority | C1: Industry | D1: Approval | E1: Aspect Ratio
A2: Not Started | B2: High | C2: Healthcare | D2: Pending | E2: 16:9
A3: Research | B3: Medium | C3: FMCG & Packaging | D3: Approved | E3: 4:5
A4: Testing | B4: Low | C4: Pet | D4: Rejected | E4: 1:1
A5: Production | B5: Watch | C5: Manufacturing | D5: Need Fix | E5: Both
A6: Uploaded | B6: Avoid | C6: Retail
A7: Paused | C7: Technology
A8: Avoid | C8: Construction
C9: Education
C10: Finance
C11: Hospitality
C12: Logistics
C13: Energy
C14: Food Advertising
C15: Office & Corporate
C16: Beauty

Sheet README
A1: Adobe Stock Intelligence Database v2
A3: Purpose | B3: Use this database to research stock-image niches before generating images.
A4: Main workflow | B4: Research niche > score opportunity > create prompts > upload > track downloads/revenue.
A5: Key sheet | B5: Niche Database
A6: Opportunity Score | B6: Calculated from Demand, inverse Competition, Commercial Value, Evergreen, Repeat Use, and inverse AI Saturation.
A7: Score guide | B7: 80+ = Invest, 60-79 = Watch, below 60 = Avoid.
A8: Next step | B8: Fill Adobe Results, Shutterstock Results, and scoring columns for 100 niches.
A9: Important | B9: Use source URLs in Source URL columns for every researched row.
A10: Google Sheets | B10: Upload this .xlsx to Google Drive, then open with Google Sheets.
A11: Reminder | B11: Do not scale image generation until a niche has evidence and a clear buyer.
A12: Version | B12: v2
